mammut/__init__.py
mammut/apps/InterpreterMain_pb2.py
mammut/apps/Protos_pb2.py
mammut/apps/WorkingMemory_pb2.py
mammut/apps/__init__.py
mammut/apps/agenda.py
mammut/apps/agenda_app.py
mammut/apps/corpus_compiler_service.py
mammut/assessment/__init__.py
mammut/assessment/assessment.py
mammut/assessment/assessor.py
mammut/assessment/mock_problem.py
mammut/assessment/problem.py
mammut/assessment/problem_type_enum.py
mammut/assessment/sentence_piece_problem.py
mammut/assessment/token_classification_problems.py
mammut/assessment/tokenizer_problems.py
mammut/assessment/util.py
mammut/common/GoogleSheetsMammutEdilmoCredentials.json
mammut/common/__init__.py
mammut/common/annotations.py
mammut/common/annotations_validator.py
mammut/common/basic_tokenizer.py
mammut/common/catalog/catalog_manager.py
mammut/common/catalog/hugging_face_datasets.py
mammut/common/constants.py
mammut/common/corpus/__init__.py
mammut/common/corpus/constants.py
mammut/common/corpus/corpus_base.py
mammut/common/corpus/corpus_map.py
mammut/common/corpus/corpus_operations.py
mammut/common/corpus/crawler_corpus.py
mammut/common/corpus/dictionary_corpus.py
mammut/common/corpus/hugging_face_corpus.py
mammut/common/corpus/images_corpus.py
mammut/common/corpus/issue_corpus.py
mammut/common/corpus/mammut_brat_document.py
mammut/common/corpus/mammut_corpus.py
mammut/common/corpus/natural_corpus.py
mammut/common/corpus/synthetic_corpus.py
mammut/common/corpus.py
mammut/common/corpus_transformer.py
mammut/common/google_api.py
mammut/common/indexer.py
mammut/common/lexicon/__init__.py
mammut/common/lexicon/dictionary.py
mammut/common/lexicon/feature.py
mammut/common/lexicon/functional.py
mammut/common/lexicon/inflection_rule.py
mammut/common/lexicon/linguistic_standard.py
mammut/common/lexicon/mammut_brat_configuration.py
mammut/common/lexicon/non_functional.py
mammut/common/lexicon/paradigm_producer.py
mammut/common/lexicon/pos.py
mammut/common/lexicon.py
mammut/common/mammut-devops-cicd.json
mammut_py-0.1.0.dev202112071923.dist-info/entry_points.txt
mammut_py-0.1.0.dev202112071923.dist-info/LICENSE
mammut_py-0.1.0.dev202112071923.dist-info/WHEEL
mammut_py-0.1.0.dev202112071923.dist-info/METADATA
mammut_py-0.1.0.dev202112071923.dist-info/RECORD
